bindata.py
distml.py
avilabsutils_ml-0.0.1.dist-info/METADATA
avilabsutils_ml-0.0.1.dist-info/WHEEL
avilabsutils_ml-0.0.1.dist-info/top_level.txt
avilabsutils_ml-0.0.1.dist-info/RECORD
