Metadata-Version: 2.1
Name: avilabsutils-ml
Version: 0.0.1
Summary: A bunch of convenience functions used for ML training.
Home-page: https://github.com/avilay/utils/ml
Author: Avilay Parekh
Author-email: avilay@gmail.com
License: UNKNOWN
Platform: UNKNOWN
Classifier: Programming Language :: Python :: 3
Classifier: License :: OSI Approved :: MIT License
Classifier: Operating System :: OS Independent
Requires-Python: >=3.6
Requires-Dist: numpy
Requires-Dist: avilabsutils-cprint
Requires-Dist: torch
Requires-Dist: scikit-learn
Requires-Dist: pandas
Requires-Dist: google-cloud-storage
